ellis_django_views/__init__.py
ellis_django_views/apps.py
ellis_django_views/views_abstract.py
ellis_django_views/views_implementation.py
ellis_django_views/migrations/0001_initial.py
ellis_django_views/migrations/__init__.py
ellis_django_views/tests/__init__.py
ellis_django_views/tests/models.py
ellis_django_views/tests/serializers.py
ellis_django_views/tests/test_views.py
ellis_django_views/tests/urls.py
ellis_django_views/tests/views.py
ellis_django_views/utils/__init__.py
ellis_django_views/utils/error_messages.py
ellis_django_views/utils/request_params.py
ellis_django_views/utils/url_names.py
ellis_django_views/utils/url_paths.py
ellis_django_views-0.1888.dist-info/LICENSE
ellis_django_views-0.1888.dist-info/METADATA
ellis_django_views-0.1888.dist-info/WHEEL
ellis_django_views-0.1888.dist-info/top_level.txt
ellis_django_views-0.1888.dist-info/RECORD
