Metadata-Version: 2.1
Name: ellis-django-views
Version: 0.1888
Summary: Generic views for Model View Serializer (MVS) pattern
Home-page: https://carlellis.io
Author: Carl Victor Ellis
Author-email: carl.ellis@hotmail.com.au
License: GNU
Platform: UNKNOWN
Classifier: Environment :: Web Environment
Classifier: Framework :: Django
Classifier: Intended Audience :: Developers
Classifier: License :: OSI Approved :: GNU General Public License v3 (GPLv3)
Classifier: Programming Language :: Python :: 3 :: Only
Classifier: Programming Language :: Python :: 3
Classifier: Programming Language :: Python :: 3.5
Classifier: Programming Language :: Python :: 3.6
Classifier: Programming Language :: Python :: 3.7
Classifier: Programming Language :: Python :: 3.8
Classifier: Operating System :: OS Independent
Classifier: Topic :: Software Development :: Libraries :: Python Modules
License-File: LICENSE
Requires-Dist: django
Requires-Dist: pillow
Requires-Dist: djangorestframework
